LICENSE
README.md
setup.py
skrm/__init__.py
skrm/__main__.py
skrm/keyring_manager.py
skrm/version.py
skrm.egg-info/PKG-INFO
skrm.egg-info/SOURCES.txt
skrm.egg-info/dependency_links.txt
skrm.egg-info/entry_points.txt
skrm.egg-info/top_level.txt