Metadata-Version: 2.1
Name: skrm
Version: 1.2.0
Summary: Simple keyring manager - Allows you to store keys associated to tags into an encrypted file, using GPG.
Home-page: https://github.com/PoncinMatthieu/skrm
Author: Matthieu Poncin
Author-email: poncin.matthieu@gmail.com
Classifier: Development Status :: 5 - Production/Stable
Classifier: Programming Language :: Python :: 3 :: Only
Classifier: License :: OSI Approved :: Apache Software License
Classifier: Operating System :: OS Independent
Classifier: Topic :: Security :: Cryptography
License-File: LICENSE
